test_pack/__init__.py
test_pack/hello_module.py
test_pack/main.py
test_pack_yasak/__init__.py
test_pack_yasak/hello_module.py
test_pack_yasak/main.py
test_pack_yasak2/__init__.py
test_pack_yasak2/hello_module.py
test_pack_yasak2/main.py
test_pack_yasak2-0.1.2.dist-info/METADATA
test_pack_yasak2-0.1.2.dist-info/WHEEL
test_pack_yasak2-0.1.2.dist-info/top_level.txt
test_pack_yasak2-0.1.2.dist-info/RECORD
