Metadata-Version: 2.1
Name: test-pack-yasak2
Version: 0.1.2
Summary: this is a test package
Home-page: UNKNOWN
Author: yasak
Author-email: yamato02031996@gmail.com
License: 42Tokyo
Platform: UNKNOWN
Requires-Python: >=3.7
